dkgr_client/__init__.py
dkgr_client/client.py
dkgr_client-0.2.2.dist-info/METADATA
dkgr_client-0.2.2.dist-info/WHEEL
dkgr_client-0.2.2.dist-info/top_level.txt
dkgr_client-0.2.2.dist-info/RECORD
