Metadata-Version: 2.2
Name: dkgr_client
Version: 0.2.2
Summary: Wrapper for dkgr backend
Home-page: https://github.com/Captain-T2004/dkgr-client
Author: Akshay Behl
Author-email: akshaybehl231@gmail.com
Classifier: Programming Language :: Python :: 3
Classifier: Operating System :: OS Independent
Requires-Python: >=3.7
Requires-Dist: requests>=2.25.0
Dynamic: author
Dynamic: author-email
Dynamic: classifier
Dynamic: description
Dynamic: description-content-type
Dynamic: home-page
Dynamic: requires-dist
Dynamic: requires-python
Dynamic: summary
